Pipelined_Adder/lpm_add_sub.v
module lpm_add_sub (dataa, datab, cin, cout, result);
	
	parameter lpm_width = 2;
	
	input [lpm_width - 1:0] dataa;
	input [lpm_width - 1:0] datab;
	input cin;

	output [lpm_width - 1:0] result;
	output cout;

	assign {cout, result} = dataa + datab + cin;
endmodule

Pipelined_Adder/lpm_ff.v

module lpm_ff(data,q,clock);
	
	parameter lpm_width =2; 
	
	input [lpm_width - 1:0] data;
	output reg [lpm_width - 1:0] q;
	input clock;

	always @(posedge clock)
	begin
		q <= data;
	end

endmodule

Pipelined_Adder/add_1p.v
// Code your design here
`include "lpm_ff.v"
`include "lpm_add_sub.v"
module add_1p( X, Y, sum, clk);

	parameter	WIDTH = 15, //Total bit width
					WIDTH1 = 7, //bit width of lsb's
					WIDTH2 = 8; //bit width 

	input [WIDTH-1:0] X, Y; //inputs
	output [WIDTH-1:0] sum; //result
	input clk; //clock

	reg [WIDTH1-1:0] I1,I2;// lsb's of input
	wire [WIDTH1-1:0] q1,r1;//lsb's of input

	reg [WIDTH2-1:0] I3, I4; //msb's of input
	wire [WIDTH2-1:0] r2, q2, u2; //MSB's of input
	
	reg [WIDTH-1:0] s; //output register
	
	wire cr1,cq1; //lsb's carry signal

	wire [WIDTH2-1:0] h2; //auxiliary msb's of input
	
	wire clkena, ADD, ena, aset, sclr; //auxiliary signal
	wire sset, aload, sload, aclr, ovf1, cin1;

	//default for add:
	assign cin1=0; assign aclr=0; assign ADD=1;
	assign ena=1; assign aclr=0; //default for FF
	assign sclr=0; assign sset=0; assign aload=0;
	assign sload=0; assign clkena=0; assign aset=0;

	//Split in MSB'S and lsb's and store in registers
	always @(posedge clk)
	begin
		//split lsb's from input x,y
		I1[WIDTH1-1:0] <= X[WIDTH1-1:0];
		I2[WIDTH1-1:0] <= Y[WIDTH1-1:0];

		//split msb's from input x,y
		I3[WIDTH2-1:0] <= X[WIDTH2-1 + WIDTH1:WIDTH1];
		I4[WIDTH2-1:0] <= Y[WIDTH2-1 + WIDTH1:WIDTH1];
	end

	/*********************First stage of Adder *************/

	
	lpm_add_sub add_1 //add lsb's of x &y
	(.result(r1), .dataa(I1), .datab(I2), .cout(cr1), .cin(cin1)); //used ports
	defparam add_1.lpm_width = WIDTH1;
	
	lpm_ff reg_1 //save lsbs of x+y 
	(.data(r1), .q(q1), .clock(clk));
	defparam reg_1.lpm_width = WIDTH1;
	
	lpm_add_sub add_2 //add msb's of x and y
	(.dataa(I3), .datab(I4), .result(r2), .cin(cin1)); // used ports
	defparam add_2.lpm_width = WIDTH2;
	//defparam add_2.lpm_direction = "add";

	lpm_ff reg_2 //save lsb's carry
	(.data(cr1), .q(cq1), .clock(clk));//used ports
	defparam reg_2.lpm_width = 1;

	lpm_ff reg_3 //Save MSB's of x+y
	(.data(r2), .q(q2), .clock(clk)); //used ports;
	defparam reg_3.lpm_width = WIDTH2;

	/**************Second stage of Adder *************/

	// One operand is zero

	assign h2 = {WIDTH2{1'b0}};

	lpm_add_sub add_3 // Add MSB's (x+y) and carry from LSB's
	(.cin(cq1), .dataa(q2), .datab(h2), .result(u2)); //used ports

	defparam add_3.lpm_width = WIDTH2;
	//defparam add_3.lpm_direction = "add";

	always @(posedge clk)
	begin
		s = {u2[WIDTH2-1:0],q1[WIDTH1-1:0]}; //output word
	end //of WIDTH=WIDTH1+WIDTH2

	assign sum = s; //Connect s to output pins

endmodule

//pg5 and the code ends

Pipelined_Adder/testbench.v
module add_1p_testbench();
  
  reg [14:0] X,Y; //inputs
  wire [14:0] sum; //result
  reg clk; //clock
   
  add_1p uut(.X(X),.Y(Y),.sum(sum),.clk(clk));
  
  always #1 clk = ~clk; //toggle clock every 1 unit of timescale
  
  initial begin
		$dumpfile("dump.vcd");
		$dumpvars();
  end
  
  initial begin
		clk = 0;
		#2;
		X = 15'd10;
		Y = 15'd00;
		#10;
		X = 15'b0000_1111_1010_010;
		Y = 15'b0000_1111_1010_010 ;
		#10;
		X = 15'b0000_1111_1111_111;
		Y = 15'b0000_1111_1111_111 ;
		#10;
		X = 15'b0000_1001_0101_010;
		Y = 15'b0000_0000_1010_111 ;
		#10;
		X = 15'b1111_1111_1111_111;
		Y = 15'b0000_0000_000_000 ;
		#10;
		X = 15'b1111_1111_1111_111;
		Y = 15'b0000_0000_000_001 ;
		#100;
		$finish;
  end
endmodule

Pipelined_Adder/dump.vcd
$date
   Sun Mar 15 18:59:26 2020
$end
$version
  P.20131013
$end
$timescale
  1ps
$end
$scope module add_1p_testbench $end
$var wire 1 Q sum [14] $end
$var wire 1 R sum [13] $end
$var wire 1 S sum [12] $end
$var wire 1 T sum [11] $end
$var wire 1 U sum [10] $end
$var wire 1 V sum [9] $end
$var wire 1 W sum [8] $end
$var wire 1 X sum [7] $end
$var wire 1 Y sum [6] $end
$var wire 1 Z sum [5] $end
$var wire 1 [ sum [4] $end
$var wire 1 \ sum [3] $end
$var wire 1 ] sum [2] $end
$var wire 1 ^ sum [1] $end
$var wire 1 _ sum [0] $end
$var reg 15 0 X [14:0] $end
$var reg 15 1 Y [14:0] $end
$var reg 1 2 clk $end
$scope module uut $end
$var wire 1 3 X [14] $end
$var wire 1 4 X [13] $end
$var wire 1 5 X [12] $end
$var wire 1 6 X [11] $end
$var wire 1 7 X [10] $end
$var wire 1 8 X [9] $end
$var wire 1 9 X [8] $end
$var wire 1 : X [7] $end
$var wire 1 ; X [6] $end
$var wire 1 < X [5] $end
$var wire 1 = X [4] $end
$var wire 1 > X [3] $end
$var wire 1 ? X [2] $end
$var wire 1 @ X [1] $end
$var wire 1 A X [0] $end
$var wire 1 B Y [14] $end
$var wire 1 C Y [13] $end
$var wire 1 D Y [12] $end
$var wire 1 E Y [11] $end
$var wire 1 F Y [10] $end
$var wire 1 G Y [9] $end
$var wire 1 H Y [8] $end
$var wire 1 I Y [7] $end
$var wire 1 J Y [6] $end
$var wire 1 K Y [5] $end
$var wire 1 L Y [4] $end
$var wire 1 M Y [3] $end
$var wire 1 N Y [2] $end
$var wire 1 O Y [1] $end
$var wire 1 P Y [0] $end
$var wire 1 Q sum [14] $end
$var wire 1 R sum [13] $end
$var wire 1 S sum [12] $end
$var wire 1 T sum [11] $end
$var wire 1 U sum [10] $end
$var wire 1 V sum [9] $end
$var wire 1 W sum [8] $end
$var wire 1 X sum [7] $end
$var wire 1 Y sum [6] $end
$var wire 1 Z sum [5] $end
$var wire 1 [ sum [4] $end
$var wire 1 \ sum [3] $end
$var wire 1 ] sum [2] $end
$var wire 1 ^ sum [1] $end
$var wire 1 _ sum [0] $end
$var wire 1 *" clk $end
$var wire 1 a q1 [6] $end
$var wire 1 b q1 [5] $end
$var wire 1 c q1 [4] $end
$var wire 1 d q1 [3] $end
$var wire 1 e q1 [2] $end
$var wire 1 f q1 [1] $end
$var wire 1 g q1 [0] $end
$var wire 1 Z! r1 [6] $end
$var wire 1 [! r1 [5] $end
$var wire 1 \! r1 [4] $end
$var wire 1 ]! r1 [3] $end
$var wire 1 ^! r1 [2] $end
$var wire 1 _! r1 [1] $end
$var wire 1 `! r1 [0] $end
$var wire 1 "" r2 [7] $end
$var wire 1 #" r2 [6] $end
$var wire 1 $" r2 [5] $end
$var wire 1 %" r2 [4] $end
$var wire 1 &" r2 [3] $end
$var wire 1 '" r2 [2] $end
$var wire 1 (" r2 [1] $end
$var wire 1 )" r2 [0] $end
$var wire 1 ," q2 [7] $end
$var wire 1 -" q2 [6] $end
$var wire 1 ." q2 [5] $end
$var wire 1 /" q2 [4] $end
$var wire 1 0" q2 [3] $end
$var wire 1 1" q2 [2] $end
$var wire 1 2" q2 [1] $end
$var wire 1 3" q2 [0] $end
$var wire 1 =" u2 [7] $end
$var wire 1 >" u2 [6] $end
$var wire 1 ?" u2 [5] $end
$var wire 1 @" u2 [4] $end
$var wire 1 A" u2 [3] $end
$var wire 1 B" u2 [2] $end
$var wire 1 C" u2 [1] $end
$var wire 1 D" u2 [0] $end
$var wire 1 }! cr1 $end
$var wire 1 <" cq1 $end
$var wire 1 4" h2 [7] $end
$var wire 1 5" h2 [6] $end
$var wire 1 6" h2 [5] $end
$var wire 1 7" h2 [4] $end
$var wire 1 8" h2 [3] $end
$var wire 1 9" h2 [2] $end
$var wire 1 :" h2 [1] $end
$var wire 1 ;" h2 [0] $end
$var wire 1 3! clkena $end
$var wire 1 4! ADD $end
$var wire 1 5! ena $end
$var wire 1 6! aset $end
$var wire 1 7! sclr $end
$var wire 1 8! sset $end
$var wire 1 9! aload $end
$var wire 1 :! sload $end
$var wire 1 ;! aclr $end
$var wire 1 <! ovf1 $end
$var wire 1 s! cin1 $end
$var reg 7 >! I1 [6:0] $end
$var reg 7 ?! I2 [6:0] $end
$var reg 8 @! I3 [7:0] $end
$var reg 8 A! I4 [7:0] $end
$var reg 15 B! s [14:0] $end
$scope module add_1 $end
$var wire 1 C! dataa [6] $end
$var wire 1 D! dataa [5] $end
$var wire 1 E! dataa [4] $end
$var wire 1 F! dataa [3] $end
$var wire 1 G! dataa [2] $end
$var wire 1 H! dataa [1] $end
$var wire 1 I! dataa [0] $end
$var wire 1 J! datab [6] $end
$var wire 1 K! datab [5] $end
$var wire 1 L! datab [4] $end
$var wire 1 M! datab [3] $end
$var wire 1 N! datab [2] $end
$var wire 1 O! datab [1] $end
$var wire 1 P! datab [0] $end
$var wire 1 s! cin $end
$var wire 1 Z! result [6] $end
$var wire 1 [! result [5] $end
$var wire 1 \! result [4] $end
$var wire 1 ]! result [3] $end
$var wire 1 ^! result [2] $end
$var wire 1 _! result [1] $end
$var wire 1 `! result [0] $end
$var wire 1 }! cout $end
$upscope $end
$scope module reg_1 $end
$var wire 1 Z! data [6] $end
$var wire 1 [! data [5] $end
$var wire 1 \! data [4] $end
$var wire 1 ]! data [3] $end
$var wire 1 ^! data [2] $end
$var wire 1 _! data [1] $end
$var wire 1 `! data [0] $end
$var wire 1 *" clock $end
$var reg 7 b! q [6:0] $end
$upscope $end
$scope module add_2 $end
$var wire 1 c! dataa [7] $end
$var wire 1 d! dataa [6] $end
$var wire 1 e! dataa [5] $end
$var wire 1 f! dataa [4] $end
$var wire 1 g! dataa [3] $end
$var wire 1 h! dataa [2] $end
$var wire 1 i! dataa [1] $end
$var wire 1 j! dataa [0] $end
$var wire 1 k! datab [7] $end
$var wire 1 l! datab [6] $end
$var wire 1 m! datab [5] $end
$var wire 1 n! datab [4] $end
$var wire 1 o! datab [3] $end
$var wire 1 p! datab [2] $end
$var wire 1 q! datab [1] $end
$var wire 1 r! datab [0] $end
$var wire 1 s! cin $end
$var wire 1 "" result [7] $end
$var wire 1 #" result [6] $end
$var wire 1 $" result [5] $end
$var wire 1 %" result [4] $end
$var wire 1 &" result [3] $end
$var wire 1 '" result [2] $end
$var wire 1 (" result [1] $end
$var wire 1 )" result [0] $end
$var wire 1 |! cout $end
$upscope $end
$scope module reg_2 $end
$var wire 1 }! data [0] $end
$var wire 1 *" clock $end
$var reg 1 !" q [0:0] $end
$upscope $end
$scope module reg_3 $end
$var wire 1 "" data [7] $end
$var wire 1 #" data [6] $end
$var wire 1 $" data [5] $end
$var wire 1 %" data [4] $end
$var wire 1 &" data [3] $end
$var wire 1 '" data [2] $end
$var wire 1 (" data [1] $end
$var wire 1 )" data [0] $end
$var wire 1 *" clock $end
$var reg 8 +" q [7:0] $end
$upscope $end
$scope module add_3 $end
$var wire 1 ," dataa [7] $end
$var wire 1 -" dataa [6] $end
$var wire 1 ." dataa [5] $end
$var wire 1 /" dataa [4] $end
$var wire 1 0" dataa [3] $end
$var wire 1 1" dataa [2] $end
$var wire 1 2" dataa [1] $end
$var wire 1 3" dataa [0] $end
$var wire 1 4" datab [7] $end
$var wire 1 5" datab [6] $end
$var wire 1 6" datab [5] $end
$var wire 1 7" datab [4] $end
$var wire 1 8" datab [3] $end
$var wire 1 9" datab [2] $end
$var wire 1 :" datab [1] $end
$var wire 1 ;" datab [0] $end
$var wire 1 <" cin $end
$var wire 1 =" result [7] $end
$var wire 1 >" result [6] $end
$var wire 1 ?" result [5] $end
$var wire 1 @" result [4] $end
$var wire 1 A" result [3] $end
$var wire 1 B" result [2] $end
$var wire 1 C" result [1] $end
$var wire 1 D" result [0] $end
$var wire 1 E" cout $end
$upscope $end
$upscope $end
$upscope $end
$enddefinitions $end
#0
$dumpvars
x[!
xg
x'"
xf
xc
xb
xa
xd
x_!
x]!
x\!
xe
x^!
xZ!
x)"
x("
x`!
x="
14!
07"
x3"
06!
x1"
x$"
x""
x?"
x0"
0;"
xB"
xA"
x."
x#"
09"
15!
07!
x&"
x2"
06"
x%"
xD"
x,"
x@"
x}!
x-"
05"
0:"
x<"
x>"
08"
x/"
xC"
04"
03!
xo!
x|!
xr!
xp!
xm!
xk!
xq!
xn!
xl!
xE"
xL
xe!
xF!
xi!
xc!
xf!
xK
xC!
xH!
xj!
xI
xN
xB
xJ!
xd!
xD
xF
0*"
xJ
xE
xC
xG!
xG
xI!
xE!
xD!
xP!
xN!
xM
xH
xM!
xK!
xL!
xg!
xO!
xh!
x_
bx 0
bx 1
02
xU
xT
xS
xR
xQ
bx >!
bx ?!
bx @!
bx A!
bx B!
x^
x]
x\
x[
xZ
xY
xX
xW
xV
x<
x6
x;
x4
0;!
x3
x?
0s!
xA
x@
x=
x:
x8
x7
x9
09!
x5
xP
08!
x>
z<!
xO
0:!
bx b!
x!"
bx +"
$end
#1000
1*"
12
#2000
0L
0K
0I
0N
0B
0D
0F
0*"
0J
0E
0C
0G
0M
0H
b1010 0
b0 1
02
0<
06
0;
04
03
0?
0A
1@
0=
0:
08
07
09
05
0P
1>
0O
#3000
0[!
0'"
1_!
1]!
0\!
0^!
0Z!
0)"
0("
0`!
0$"
0""
0#"
0&"
0%"
0}!
0o!
0|!
0r!
0p!
0m!
0k!
0q!
0n!
0l!
0e!
1F!
0i!
0c!
0f!
0C!
1H!
0j!
0J!
0d!
1*"
0G!
0I!
0E!
0D!
0P!
0N!
0M!
0K!
0L!
0g!
0O!
0h!
12
b1010 >!
b0 ?!
b0 @!
b0 A!
#4000
0*"
02
#5000
0g
1f
0c
0b
0a
1d
0e
0="
03"
01"
0?"
00"
0B"
0A"
0."
02"
0D"
0,"
0@"
0-"
0<"
0>"
0/"
0C"
0E"
1*"
12
b1010 b!
0!"
b0 +"
#6000
0*"
02
#7000
1*"
0_
12
0U
0T
0S
0R
0Q
b1010 B!
1^
0]
1\
0[
0Z
0Y
0X
0W
0V
#8000
0*"
02
#9000
1*"
12
#10000
0*"
02
#11000
1*"
12
#12000
1L
1I
1F
0*"
1J
1G
1H
b11111010010 0
b11111010010 1
02
1;
1=
1:
18
17
19
0>
1O
#13000
1[!
1'"
0_!
0]!
1^!
1("
1&"
1%"
1}!
1o!
1r!
1p!
1q!
0F!
1i!
1C!
1j!
1J!
1*"
1E!
1L!
1g!
1O!
1h!
12
b1010010 >!
b1010010 ?!
b1111 @!
b1111 A!
#14000
0*"
02
#15000
0f
1b
0d
1e
11"
10"
1B"
1A"
12"
1D"
1@"
1<"
1/"
1C"
1*"
12
b100100 b!
1!"
b11110 +"
#16000
0*"
02
#17000
1*"
12
1U
1T
b111110100100 B!
0^
1]
0\
1Z
1X
1W
1V
#18000
0*"
02
#19000
1*"
12
#20000
0*"
02
#21000
1*"
12
#22000
1K
1N
0*"
1M
b11111111111 0
b11111111111 1
02
1<
1?
1A
1P
1>
#23000
1_!
1]!
1\!
1Z!
1F!
1*"
1G!
1I!
1D!
1P!
1N!
1M!
1K!
12
b1111111 >!
b1111111 ?!
#24000
0*"
02
#25000
1f
1c
1a
1d
1*"
12
b1111110 b!
#26000
0*"
02
#27000
1*"
12
b111111111110 B!
1^
1\
1[
1Y
#28000
0*"
02
#29000
1*"
12
#30000
0*"
02
#31000
1*"
12
#32000
0K
0I
0F
0*"
0G
0M
0H
b10010101010 0
b1010111 1
02
0;
0?
0A
0=
08
09
#33000
0[!
0'"
0_!
0]!
0\!
0^!
0Z!
1)"
0("
1`!
0%"
0o!
0r!
0p!
0q!
0i!
0C!
1*"
0G!
0I!
0E!
0M!
0K!
0h!
12
b101010 >!
b1010111 ?!
b1001 @!
b0 A!
#34000
0*"
02
#35000
1g
0f
0c
0b
0a
0d
0e
13"
01"
0B"
02"
0D"
0@"
0/"
1*"
12
b1 b!
b1001 +"
#36000
0*"
02
#37000
1*"
1_
12
0T
b10100000001 B!
0^
0]
0\
0[
0Z
0Y
0X
0V
#38000
0*"
02
#39000
1*"
12
#40000
0*"
02
#41000
1*"
12
#42000
0L
0N
0*"
0J
b111111111111111 0
b0 1
02
16
1;
14
13
1?
1A
1=
18
19
15
0P
0O
#43000
1[!
1'"
1_!
1]!
1\!
1^!
1Z!
1("
1$"
1""
1#"
1%"
0}!
1e!
1i!
1c!
1f!
1C!
0J!
1d!
1*"
1G!
1I!
1E!
0P!
0N!
0L!
0O!
1h!
12
b1111111 >!
b0 ?!
b11111111 @!
#44000
0*"
02
#45000
1f
1c
1b
1a
1d
1e
1="
11"
1?"
1B"
1."
12"
1D"
1,"
1@"
1-"
0<"
1>"
1/"
1*"
12
b1111111 b!
0!"
b11111111 +"
#46000
0*"
02
#47000
1*"
12
1T
1S
1R
1Q
b111111111111111 B!
1^
1]
1\
1[
1Z
1Y
1X
1V
#48000
0*"
02
#49000
1*"
12
#50000
0*"
02
#51000
1*"
12
#52000
0*"
b1 1
02
1P
#53000
0[!
0_!
0]!
0\!
0^!
0Z!
0`!
1}!
1*"
1P!
12
b1 ?!
#54000
0*"
02
#55000
0g
0f
0c
0b
0a
0d
0e
0="
0?"
0B"
0A"
0D"
0@"
1<"
0>"
0C"
1E"
1*"
12
b0 b!
1!"
#56000
0*"
02
#57000
1*"
0_
12
0U
0T
0S
0R
0Q
b0 B!
0^
0]
0\
0[
0Z
0Y
0X
0W
0V
