Pipelined_Adder/lpm_add_sub_8bit.v
module lpm_add_sub_8bit(dataa,datab,cin,cout,result);

parameter lpm_width=7;
parameter lpm_direction="add";

input [7:0]dataa;
input [7:0]datab;
output [7:0]result;
output cout;
input cin;
/*
reg [7:0] temp;
	
	assign temp = dataa + datab + cin;
	assign result = temp[6:0];
	assign cout = temp[7];
*/
	assign {cout, result} = dataa + datab + cin;
endmodule

Pipelined_Adder/lpm_ff_8bit.v
module lpm_ff_8bit(data,q,clock);
parameter lpm_width = 7; 
input [7:0]data;
output reg [7:0]q;
input clock;

always @(posedge clock)
begin
q <= data;
end

endmodule

Pipelined_Adder/lpm_ff.v

module lpm_ff(data,q,clock);
	
	parameter lpm_width =2; 
	
	input [lpm_width - 1:0] data;
	output reg [lpm_width - 1:0] q;
	input clock;

	always @(posedge clock)
	begin
		q <= data;
	end

endmodule

Pipelined_Adder/lpm_add_sub.v
module lpm_add_sub (dataa, datab, cin, cout, result);
	
	parameter lpm_width = 2;
	
	input [lpm_width - 1:0] dataa;
	input [lpm_width - 1:0] datab;
	input cin;

	output [lpm_width - 1:0] result;
	output cout;

	assign {cout, result} = dataa + datab + cin;
endmodule

Pipelined_Adder/add_1p.v
// Code your design here
`include "lpm_ff.v"
`include "lpm_add_sub.v"
module add_1p(X,Y,sum,clk);
  parameter   WIDTH = 15, //Total bit width
				  WIDTH1 = 7, //bit width of lsb's
				  WIDTH2 = 8; //bit width 
  
  input [WIDTH-1:0] X,Y; //inputs
  output [WIDTH-1:0] sum; //result
  input clk; //clock
  
  reg [WIDTH1-1:0] I1,I2;// lsb's of input
  wire [WIDTH1-1:0] q1,r1;//lsb's of input

  reg [WIDTH2-1:0] I3, I4; //msb's of input
  wire [WIDTH2-1:0] r2, q2, u2; //MSB's of input
  reg [WIDTH-1:0] s; //output register
  wire cr1,cq1; //lsb's carry signal
  //pg1 ends
  
  
  wire [WIDTH2-1:0]h2; //auxiliary msb's of input
  wire clkena, ADD, ena, aset, sclr; //auxiliary signal
  wire sset, aload, sload, aclr, ovf1, cin1;
  
  //default for add:
  assign cin1=0; assign aclr=0; assign ADD=1;
  assign ena=1; assign aclr=0; //default for FF
  assign sclr=0; assign sset=0; assign aload=0;
  assign sload=0; assign clkena=0; assign aset=0;
  
  //Split in MSB'S and lsb's and store in registers
  always @(posedge clk)
    begin
      //split lsb's from input x,y
      I1[WIDTH1-1:0] <= X[WIDTH1-1:0];
      I2[WIDTH1-1:0] <= Y[WIDTH1-1:0];
      //split msb's from input x,y
      I3[WIDTH2-1:0] <= X[WIDTH2-1 + WIDTH1:WIDTH1];
      I4[WIDTH2-1:0] <= Y[WIDTH2-1 + WIDTH1:WIDTH1];
    end
  //pg2 ends
  
  /*********************First stage of Adder *************/
  
  lpm_add_sub add_1 //add lsb's of x &y
  (.result(r1), .dataa(I1), .datab(I2), .cout(cr1), .cin(cin1)); //used ports
  //.overflow(ovl1), .clken(clkena), .add_sub(ADD),
  //.cin(cin1), .clock(clk), .aclr(aclr); //unused ports
  
  defparam add_1.lpm_width = WIDTH1;
  defparam add_1.lpm_direction = "add";
  
  lpm_ff reg_1 //save lsbs of x+y
  (.data(r1), .q(q1), .clock(clk)); //used ports
  //enable(ena), .aclr(.aclr), .aset(aset), .sclr(sclr),
  //.sset(sset), .aload(aload), .sload(sload)); //unused ports
  defparam reg_1.lpm_width = WIDTH1;
  
  lpm_ff reg_2 //save lsb's carry
  (.data({6'b000000,cr1}), .q(cq1), .clock(clk));//used ports
  
  //.enable(ena), .aclr(aclr), .aset(aset), .sclr(sclr),
  //.sset(sset), .aload(aload), .sload(sload)); //unused ports
  defparam reg_2.lpm_width = 1;
  //pg3 ends
  
  lpm_add_sub_8bit add_2 //add msb's of x and y
  (.dataa(I3), .datab(I4), .result(r2), .cin(cin1)); // used ports
  //.add_sub(ADD), .cout(cout1), .cin(cin1), .clken(clkena),
  // .overflow(ovl1), .clock(clk), .aclr(aclr)); //unused
  
  defparam add_2.lpm_width = WIDTH2;
  defparam add_2.lpm_direction = "add";
  
  lpm_ff_8bit reg_3 //Save MSB's of x+y
  (.data(r2), .q(q2), .clock(clk)); //used ports;
  
  //.enable(ena), .aclr(aclr), .aset(aset), .sclr(sclr),
  //.sset(sset), .aload(aload), .sload(sload)); //Unused
  
  defparam reg_3.lpm_width = WIDTH2;
  
  //pg4 ends
  
    /**************Second stage of Adder *************/
  
  // One operand is zero
  
  assign h2 = {WIDTH2{1'b0}};
  
  lpm_add_sub_8bit add_3 // Add MSB's (x+y) and carry from LSB's
  (.cin(cq1), .dataa(q2), .datab(h2), .result(u2)); //used ports
  
  //.cout(cout1), .overflow(ovl1), .clken(clena),//unused 
  //.add_sub(ADD), .clock(clk), .aclr(aclr)); //ports
  
  defparam add_3.lpm_width = WIDTH2;
  defparam add_3.lpm_direction = "add";
  
  always @(posedge clk)
    begin
      s = {u2[WIDTH2-1:0],q1[WIDTH1-1:0]}; //output word
    end //of WIDTH=WIDTH1+WIDTH2

  assign sum = s; //Connect s to output pins
  
endmodule

  //pg5 and the code ends

Pipelined_Adder/testbench.v
module add_1p_testbench();
  
  reg [14:0] X,Y; //inputs
  wire [14:0] sum; //result
  reg clk; //clock
   
  add_1p uut(.X(X),.Y(Y),.sum(sum),.clk(clk));
  
  always #1 clk = ~clk;
  
  initial begin
		$monitor("X=%d, Y=%d, sum=%d", X, Y, sum);
  end
  
  initial begin
		$dumpfile("dump.vcd");
		$dumpvars();
  end
  
  initial begin
		clk = 0;
		#2;
		X = 15'd10;
		Y = 15'd00;
		#10;
		X = 15'b0000_1111_1010_010;
		Y = 15'b0000_1111_1010_010 ;
		#10;
		repeat(3)
		begin
			X= $random;
			Y= $random;
			#100;
		end
		#1000;
		$finish;
  end
  
endmodule

Pipelined_Adder/dump.vcd
$date
   Wed Mar 04 15:51:21 2020
$end
$version
  P.20131013
$end
$timescale
  1ps
$end
$scope module add_1p_testbench $end
$var wire 1 Q sum [14] $end
$var wire 1 R sum [13] $end
$var wire 1 S sum [12] $end
$var wire 1 T sum [11] $end
$var wire 1 U sum [10] $end
$var wire 1 V sum [9] $end
$var wire 1 W sum [8] $end
$var wire 1 X sum [7] $end
$var wire 1 Y sum [6] $end
$var wire 1 Z sum [5] $end
$var wire 1 [ sum [4] $end
$var wire 1 \ sum [3] $end
$var wire 1 ] sum [2] $end
$var wire 1 ^ sum [1] $end
$var wire 1 _ sum [0] $end
$var reg 15 0 X [14:0] $end
$var reg 15 1 Y [14:0] $end
$var reg 1 2 clk $end
$scope module uut $end
$var wire 1 3 X [14] $end
$var wire 1 4 X [13] $end
$var wire 1 5 X [12] $end
$var wire 1 6 X [11] $end
$var wire 1 7 X [10] $end
$var wire 1 8 X [9] $end
$var wire 1 9 X [8] $end
$var wire 1 : X [7] $end
$var wire 1 ; X [6] $end
$var wire 1 < X [5] $end
$var wire 1 = X [4] $end
$var wire 1 > X [3] $end
$var wire 1 ? X [2] $end
$var wire 1 @ X [1] $end
$var wire 1 A X [0] $end
$var wire 1 B Y [14] $end
$var wire 1 C Y [13] $end
$var wire 1 D Y [12] $end
$var wire 1 E Y [11] $end
$var wire 1 F Y [10] $end
$var wire 1 G Y [9] $end
$var wire 1 H Y [8] $end
$var wire 1 I Y [7] $end
$var wire 1 J Y [6] $end
$var wire 1 K Y [5] $end
$var wire 1 L Y [4] $end
$var wire 1 M Y [3] $end
$var wire 1 N Y [2] $end
$var wire 1 O Y [1] $end
$var wire 1 P Y [0] $end
$var wire 1 Q sum [14] $end
$var wire 1 R sum [13] $end
$var wire 1 S sum [12] $end
$var wire 1 T sum [11] $end
$var wire 1 U sum [10] $end
$var wire 1 V sum [9] $end
$var wire 1 W sum [8] $end
$var wire 1 X sum [7] $end
$var wire 1 Y sum [6] $end
$var wire 1 Z sum [5] $end
$var wire 1 [ sum [4] $end
$var wire 1 \ sum [3] $end
$var wire 1 ] sum [2] $end
$var wire 1 ^ sum [1] $end
$var wire 1 _ sum [0] $end
$var wire 1 0" clk $end
$var wire 1 a q1 [6] $end
$var wire 1 b q1 [5] $end
$var wire 1 c q1 [4] $end
$var wire 1 d q1 [3] $end
$var wire 1 e q1 [2] $end
$var wire 1 f q1 [1] $end
$var wire 1 g q1 [0] $end
$var wire 1 Z! r1 [6] $end
$var wire 1 [! r1 [5] $end
$var wire 1 \! r1 [4] $end
$var wire 1 ]! r1 [3] $end
$var wire 1 ^! r1 [2] $end
$var wire 1 _! r1 [1] $end
$var wire 1 `! r1 [0] $end
$var wire 1 (" r2 [7] $end
$var wire 1 )" r2 [6] $end
$var wire 1 *" r2 [5] $end
$var wire 1 +" r2 [4] $end
$var wire 1 ," r2 [3] $end
$var wire 1 -" r2 [2] $end
$var wire 1 ." r2 [1] $end
$var wire 1 /" r2 [0] $end
$var wire 1 2" q2 [7] $end
$var wire 1 3" q2 [6] $end
$var wire 1 4" q2 [5] $end
$var wire 1 5" q2 [4] $end
$var wire 1 6" q2 [3] $end
$var wire 1 7" q2 [2] $end
$var wire 1 8" q2 [1] $end
$var wire 1 9" q2 [0] $end
$var wire 1 B" u2 [7] $end
$var wire 1 C" u2 [6] $end
$var wire 1 D" u2 [5] $end
$var wire 1 E" u2 [4] $end
$var wire 1 F" u2 [3] $end
$var wire 1 G" u2 [2] $end
$var wire 1 H" u2 [1] $end
$var wire 1 I" u2 [0] $end
$var wire 1 X! cr1 $end
$var wire 1 K" cq1 $end
$var wire 1 :" h2 [7] $end
$var wire 1 ;" h2 [6] $end
$var wire 1 <" h2 [5] $end
$var wire 1 =" h2 [4] $end
$var wire 1 >" h2 [3] $end
$var wire 1 ?" h2 [2] $end
$var wire 1 @" h2 [1] $end
$var wire 1 A" h2 [0] $end
$var wire 1 3! clkena $end
$var wire 1 4! ADD $end
$var wire 1 5! ena $end
$var wire 1 6! aset $end
$var wire 1 7! sclr $end
$var wire 1 8! sset $end
$var wire 1 9! aload $end
$var wire 1 :! sload $end
$var wire 1 ;! aclr $end
$var wire 1 <! ovf1 $end
$var wire 1 '" cin1 $end
$var reg 7 >! I1 [6:0] $end
$var reg 7 ?! I2 [6:0] $end
$var reg 8 @! I3 [7:0] $end
$var reg 8 A! I4 [7:0] $end
$var reg 15 B! s [14:0] $end
$scope module add_1 $end
$var wire 1 C! dataa [6] $end
$var wire 1 D! dataa [5] $end
$var wire 1 E! dataa [4] $end
$var wire 1 F! dataa [3] $end
$var wire 1 G! dataa [2] $end
$var wire 1 H! dataa [1] $end
$var wire 1 I! dataa [0] $end
$var wire 1 J! datab [6] $end
$var wire 1 K! datab [5] $end
$var wire 1 L! datab [4] $end
$var wire 1 M! datab [3] $end
$var wire 1 N! datab [2] $end
$var wire 1 O! datab [1] $end
$var wire 1 P! datab [0] $end
$var wire 1 Z! result [6] $end
$var wire 1 [! result [5] $end
$var wire 1 \! result [4] $end
$var wire 1 ]! result [3] $end
$var wire 1 ^! result [2] $end
$var wire 1 _! result [1] $end
$var wire 1 `! result [0] $end
$var wire 1 X! cout $end
$var wire 1 '" cin $end
$upscope $end
$scope module reg_1 $end
$var wire 1 Z! data [6] $end
$var wire 1 [! data [5] $end
$var wire 1 \! data [4] $end
$var wire 1 ]! data [3] $end
$var wire 1 ^! data [2] $end
$var wire 1 _! data [1] $end
$var wire 1 `! data [0] $end
$var wire 1 0" clock $end
$var reg 7 b! q [6:0] $end
$upscope $end
$scope module reg_2 $end
$var wire 1 c! data [6] $end
$var wire 1 d! data [5] $end
$var wire 1 e! data [4] $end
$var wire 1 f! data [3] $end
$var wire 1 g! data [2] $end
$var wire 1 h! data [1] $end
$var wire 1 i! data [0] $end
$var wire 1 0" clock $end
$var reg 7 k! q [6:0] $end
$upscope $end
$scope module add_2 $end
$var wire 1 l! dataa [7] $end
$var wire 1 m! dataa [6] $end
$var wire 1 n! dataa [5] $end
$var wire 1 o! dataa [4] $end
$var wire 1 p! dataa [3] $end
$var wire 1 q! dataa [2] $end
$var wire 1 r! dataa [1] $end
$var wire 1 s! dataa [0] $end
$var wire 1 t! datab [7] $end
$var wire 1 u! datab [6] $end
$var wire 1 v! datab [5] $end
$var wire 1 w! datab [4] $end
$var wire 1 x! datab [3] $end
$var wire 1 y! datab [2] $end
$var wire 1 z! datab [1] $end
$var wire 1 {! datab [0] $end
$var wire 1 (" result [7] $end
$var wire 1 )" result [6] $end
$var wire 1 *" result [5] $end
$var wire 1 +" result [4] $end
$var wire 1 ," result [3] $end
$var wire 1 -" result [2] $end
$var wire 1 ." result [1] $end
$var wire 1 /" result [0] $end
$var wire 1 &" cout $end
$var wire 1 '" cin $end
$upscope $end
$scope module reg_3 $end
$var wire 1 (" data [7] $end
$var wire 1 )" data [6] $end
$var wire 1 *" data [5] $end
$var wire 1 +" data [4] $end
$var wire 1 ," data [3] $end
$var wire 1 -" data [2] $end
$var wire 1 ." data [1] $end
$var wire 1 /" data [0] $end
$var wire 1 0" clock $end
$var reg 8 1" q [7:0] $end
$upscope $end
$scope module add_3 $end
$var wire 1 2" dataa [7] $end
$var wire 1 3" dataa [6] $end
$var wire 1 4" dataa [5] $end
$var wire 1 5" dataa [4] $end
$var wire 1 6" dataa [3] $end
$var wire 1 7" dataa [2] $end
$var wire 1 8" dataa [1] $end
$var wire 1 9" dataa [0] $end
$var wire 1 :" datab [7] $end
$var wire 1 ;" datab [6] $end
$var wire 1 <" datab [5] $end
$var wire 1 =" datab [4] $end
$var wire 1 >" datab [3] $end
$var wire 1 ?" datab [2] $end
$var wire 1 @" datab [1] $end
$var wire 1 A" datab [0] $end
$var wire 1 B" result [7] $end
$var wire 1 C" result [6] $end
$var wire 1 D" result [5] $end
$var wire 1 E" result [4] $end
$var wire 1 F" result [3] $end
$var wire 1 G" result [2] $end
$var wire 1 H" result [1] $end
$var wire 1 I" result [0] $end
$var wire 1 J" cout $end
$var wire 1 K" cin $end
$upscope $end
$upscope $end
$upscope $end
$enddefinitions $end
#0
$dumpvars
x4
xP!
xN!
xL!
xM!
xK!
00"
xJ!
xI
xO!
x3
xC
xN
xL
x5
xK
xF
xE
xD
xB
xO
xH!
xI!
xD!
xH
xC!
xP
xJ
xG!
xF!
xE!
xM
xG
x^
x]
x\
x[
xZ
xY
xX
xW
xV
xU
x_
bx 0
bx 1
02
xT
xS
xR
xQ
xg
xf
bx >!
bx ?!
bx @!
bx A!
bx B!
xa
x\!
xd
xb
x/"
x."
xc
x_!
x]!
x[!
xZ!
x-"
x^!
x`!
x+"
xe
x,"
x6"
15!
06!
07!
x("
x9"
xG"
08!
09!
x8"
xH"
xF"
0@"
x*"
x)"
xD"
x3"
0A"
x4"
xE"
0?"
0>"
xX!
x7"
0="
0<"
xI"
x5"
x2"
xB"
0:"
xC"
xK"
0;"
03!
14!
0f!
0d!
xA
x<
0h!
x:
0'"
x@
x9
0e!
0:!
x?
x8
z<!
x7
x6
0g!
x>
0;!
x;
x=
0c!
xi!
bx b!
bx k!
bx 1"
xm!
xp!
x&"
xy!
xo!
xJ"
xz!
xv!
xu!
xq!
x{!
xn!
xl!
xs!
xx!
xt!
xr!
xw!
$end
#1000
10"
12
b0x k!
#2000
04
00"
0I
03
0C
0N
0L
05
0K
0F
0E
0D
0B
0O
0H
0P
0J
0M
0G
b1010 0
b0 1
02
0A
0<
0:
1@
09
0?
08
07
06
1>
0;
0=
#3000
0P!
0N!
0L!
0M!
0K!
10"
0J!
0O!
1H!
0I!
0D!
0C!
0G!
1F!
0E!
12
b1010 >!
b0 ?!
b0 @!
b0 A!
0\!
0/"
0."
1_!
1]!
0[!
0Z!
0-"
0^!
0`!
0+"
0,"
0("
0*"
0)"
0X!
0i!
0m!
0p!
0&"
0y!
0o!
0z!
0v!
0u!
0q!
0{!
0n!
0l!
0s!
0x!
0t!
0r!
0w!
#4000
00"
02
#5000
10"
12
0g
1f
0a
1d
0b
0c
0e
06"
09"
0G"
08"
0H"
0F"
0D"
03"
04"
0E"
07"
0I"
05"
02"
0B"
0C"
0K"
b1010 b!
b0 k!
b0 1"
0J"
#6000
00"
02
#7000
10"
1^
0]
1\
0[
0Z
0Y
0X
0W
0V
0U
0_
12
0T
0S
0R
0Q
b1010 B!
#8000
00"
02
#9000
10"
12
#10000
00"
02
#11000
10"
12
#12000
00"
1I
1L
1F
1O
1H
1J
1G
b11111010010 0
b11111010010 1
02
1:
19
18
17
0>
1;
1=
#13000
1L!
10"
1J!
1O!
1C!
0F!
1E!
12
b1010010 >!
b1010010 ?!
b1111 @!
b1111 A!
1."
0_!
0]!
1[!
1-"
1^!
1+"
1,"
1X!
1i!
1p!
1y!
1z!
1q!
1{!
1s!
1x!
1r!
#14000
00"
02
#15000
10"
12
0f
0d
1b
1e
16"
1G"
18"
1H"
1F"
1E"
17"
1I"
15"
1K"
b100100 b!
b1 k!
b11110 1"
#16000
00"
02
#17000
10"
0^
1]
0\
1Z
1X
1W
1V
1U
12
1T
b111110100100 B!
#18000
00"
02
#19000
10"
12
#20000
00"
02
#21000
10"
12
#22000
14
00"
0L
15
1E
1D
1B
0O
0H
1P
0J
b11010100100100 0
b101111010000001 1
02
1<
0:
0@
1?
08
0;
0=
#23000
1P!
0L!
10"
0J!
0O!
0H!
1D!
0C!
1G!
0E!
12
b100100 >!
b1 ?!
b1101010 @!
b10111101 A!
1/"
1`!
0+"
0,"
1*"
0X!
0i!
1m!
1&"
0z!
1v!
0q!
1n!
0s!
1t!
1w!
#24000
00"
02
#25000
10"
12
1g
06"
19"
0F"
1D"
14"
0E"
05"
0K"
b100101 b!
b0 k!
b100111 1"
#26000
00"
02
#27000
10"
0U
1_
12
0T
1S
b1001110100101 B!
