Pipelined_Adder/lpm_add_sub.v
module lpm_add_sub(dataa,datab,cin,cout,result);

parameter lpm_width=7;
parameter lpm_direction="add";

input [6:0]dataa;
input [6:0]datab;
output [6:0]result;
output cout;
input cin;
 assign {cout, result} = dataa + datab;

endmodule

Pipelined_Adder/lpm_ff.v
module lpm_ff(data,q,clock);
parameter lpm_width = 7; 
input [6:0]data;
output reg [6:0]q;
input clock;

always @(posedge clock)
begin
q <= data;
end

endmodule

Pipelined_Adder/add_1p.v
// Code your design here
`include "lpm_ff.v"
`include "lpm_add_sub.v"
module add_1p(X,Y,sum,clk);
  parameter WIDTH = 15, //Total bit width
  WIDTH1 = 7, //bit width of lsb's
  WIDTH2 = 8; //bit width 
  
  input [WIDTH-1:0] X,Y; //inputs
  output [WIDTH-1:0] sum; //result
  input clk; //clock
  
  reg [WIDTH1-1:0] I1,I2;// lsb's of input
  
  wire [WIDTH1-1:0] q1,r1;//lsb's of input
  reg [WIDTH2-1:0] I3, I4; //msb's of input
  wire [WIDTH2-1:0] r2, q2, u2; //MSB's of input
  reg [WIDTH-1:0] s; //output register
  wire cr1,cq1; //lsb's carry signal
  //pg1 ends
  
  
  wire [WIDTH2-1:0]h2; //auxiliary msb's of input
  wire clkena, ADD, ena, aset, sclr; //auxiliary signal
  wire sset, aload, sload, aclr, ovf1, cin1;
  
  //default for add:
  assign cin1=0; assign aclr=0; assign ADD=1;
  assign ena=1; assign aclr=0; //default for FF
  assign sclr=0; assign sset=0; assign aload=0;
  assign sload=0; assign clkena=0; assign aset=0;
  
  //Split in MSB'S and lsb's and store in registers
  always @(posedge clk)
    begin
      //split lsb's from input x,y
      I1[WIDTH1-1:0] <= X[WIDTH1-1:0];
      I2[WIDTH1-1:0] <= Y[WIDTH1-1:0];
      //split msb's from input x,y
      I3[WIDTH2-1:0] <= X[WIDTH2-1 + WIDTH1:WIDTH1];
      I4[WIDTH2-1:0] <= Y[WIDTH2-1 + WIDTH1:WIDTH1];
    end
  //pg2 ends
  
  /*********************First stage of Adder *************/
  
  lpm_add_sub add_1 //add lsb's of x &y
  (.result(r1), .dataa(I1), .datab(I2), .cout(cr1)); //used ports
  //.overflow(ovl1), .clken(clkena), .add_sub(ADD),
  //.cin(cin1), .clock(clk), .aclr(aclr); //unused ports
  
  defparam add_1.lpm_width = WIDTH1;
  defparam add_1.lpm_direction = "add";
  
  lpm_ff reg_1 //save lsbs of x+y
  (.data(r1), .q(q1), .clock(clk)); //used ports
  //enable(ena), .aclr(.aclr), .aset(aset), .sclr(sclr),
  //.sset(sset), .aload(aload), .sload(sload)); //unused ports
  defparam reg_1.lpm_width = WIDTH1;
  
  lpm_ff reg_2 //save lsb's carry
  (.data(cr1), .q(cq1), .clock(clk));//used ports
  
  //.enable(ena), .aclr(aclr), .aset(aset), .sclr(sclr),
  //.sset(sset), .aload(aload), .sload(sload)); //unused ports
  defparam reg_2.lpm_width = 1;
  //pg3 ends
  
  lpm_add_sub add_2 //add msb's of x and y
  (.dataa(I3), .datab(I4), .result(r2)); // used ports
  //.add_sub(ADD), .cout(cout1), .cin(cin1), .clken(clkena),
  // .overflow(ovl1), .clock(clk), .aclr(aclr)); //unused
  
  defparam add_2.lpm_width = WIDTH2;
  defparam add_2.lpm_direction = "add";
  
  lpm_ff reg_3 //Save MSB's of x+y
  (.data(r2), .q(q2), .clock(clk)); //used ports;
  
  //.enable(ena), .aclr(aclr), .aset(aset), .sclr(sclr),
  //.sset(sset), .aload(aload), .sload(sload)); //Unused
  
  defparam reg_3.lpm_width = WIDTH2;
  
  //pg4 ends
  
    /**************Second stage of Adder *************/
  
  // One operand is zero
  
  assign h2 = {WIDTH2{1'b0}};
  
  lpm_add_sub add_3 // Add MSB's (x+y) and carry from LSB's
  (.cin(cq1), .dataa(q2), .datab(h2), .result(U2)); //used ports
  
  //.cout(cout1), .overflow(ovl1), .clken(clena),//unused 
  //.add_sub(ADD), .clock(clk), .aclr(aclr)); //ports
  
  defparam add_3.lpm_width = WIDTH2;
  defparam add_3.lpm_direction = "add";
  
  always @(posedge clk)
    begin
      s = {u2[WIDTH2-1:0],q1[WIDTH1-1:0]}; //output word
    end //of WIDTH=WIDTH1+WIDTH2

  assign sum = s; //Connect s to output pins
  
endmodule

  //pg5 and the code ends

Pipelined_Adder/testbench.v
module add_1p_testbench();
  
  reg [14:0] X,Y; //inputs
  wire [14:0] sum; //result
  reg clk; //clock
   
  add_1p uut(.X(X),.Y(Y),.sum(sum),.clk(clk));
  
  always #1 clk = ~clk;
  
  initial begin
		$monitor("X=%d, Y=%d, sum=%d", X, Y, sum);
  end
  
  initial begin
		$dumpfile("dump.vcd");
		$dumpvars();
  end
  
  initial begin
		clk = 0;
		#5;
		X = 14'd10;
		Y = 14'd00;
		#10;
		X = 14'b0000_1111_1010_01;
		Y = 14'b0000_1111_1010_01 ;
		#10;
		X = 14'b1111_0000_0101_11 ;
		Y = 14'b1111_0000_1010_10 ;
		#10;
		X = 14'b1111_1010_0000_11 ;
		Y = 14'b0000_1111_1111_11 ;
		#1000;
		$finish;
  end
  
endmodule

Pipelined_Adder/dump.vcd
$date
   Mon Mar 02 23:43:47 2020
$end
$version
  P.20131013
$end
$timescale
  1ps
$end
$scope module add_1p_testbench $end
$var wire 1 Q sum [14] $end
$var wire 1 R sum [13] $end
$var wire 1 S sum [12] $end
$var wire 1 T sum [11] $end
$var wire 1 U sum [10] $end
$var wire 1 V sum [9] $end
$var wire 1 W sum [8] $end
$var wire 1 X sum [7] $end
$var wire 1 Y sum [6] $end
$var wire 1 Z sum [5] $end
$var wire 1 [ sum [4] $end
$var wire 1 \ sum [3] $end
$var wire 1 ] sum [2] $end
$var wire 1 ^ sum [1] $end
$var wire 1 _ sum [0] $end
$var reg 15 0 X [14:0] $end
$var reg 15 1 Y [14:0] $end
$var reg 1 2 clk $end
$scope module uut $end
$var wire 1 3 X [14] $end
$var wire 1 4 X [13] $end
$var wire 1 5 X [12] $end
$var wire 1 6 X [11] $end
$var wire 1 7 X [10] $end
$var wire 1 8 X [9] $end
$var wire 1 9 X [8] $end
$var wire 1 : X [7] $end
$var wire 1 ; X [6] $end
$var wire 1 < X [5] $end
$var wire 1 = X [4] $end
$var wire 1 > X [3] $end
$var wire 1 ? X [2] $end
$var wire 1 @ X [1] $end
$var wire 1 A X [0] $end
$var wire 1 B Y [14] $end
$var wire 1 C Y [13] $end
$var wire 1 D Y [12] $end
$var wire 1 E Y [11] $end
$var wire 1 F Y [10] $end
$var wire 1 G Y [9] $end
$var wire 1 H Y [8] $end
$var wire 1 I Y [7] $end
$var wire 1 J Y [6] $end
$var wire 1 K Y [5] $end
$var wire 1 L Y [4] $end
$var wire 1 M Y [3] $end
$var wire 1 N Y [2] $end
$var wire 1 O Y [1] $end
$var wire 1 P Y [0] $end
$var wire 1 Q sum [14] $end
$var wire 1 R sum [13] $end
$var wire 1 S sum [12] $end
$var wire 1 T sum [11] $end
$var wire 1 U sum [10] $end
$var wire 1 V sum [9] $end
$var wire 1 W sum [8] $end
$var wire 1 X sum [7] $end
$var wire 1 Y sum [6] $end
$var wire 1 Z sum [5] $end
$var wire 1 [ sum [4] $end
$var wire 1 \ sum [3] $end
$var wire 1 ] sum [2] $end
$var wire 1 ^ sum [1] $end
$var wire 1 _ sum [0] $end
$var wire 1 -" clk $end
$var wire 1 a q1 [6] $end
$var wire 1 b q1 [5] $end
$var wire 1 c q1 [4] $end
$var wire 1 d q1 [3] $end
$var wire 1 e q1 [2] $end
$var wire 1 f q1 [1] $end
$var wire 1 g q1 [0] $end
$var wire 1 [! r1 [6] $end
$var wire 1 \! r1 [5] $end
$var wire 1 ]! r1 [4] $end
$var wire 1 ^! r1 [3] $end
$var wire 1 _! r1 [2] $end
$var wire 1 `! r1 [1] $end
$var wire 1 a! r1 [0] $end
$var wire 1 o r2 [7] $end
$var wire 1 &" r2 [6] $end
$var wire 1 '" r2 [5] $end
$var wire 1 (" r2 [4] $end
$var wire 1 )" r2 [3] $end
$var wire 1 *" r2 [2] $end
$var wire 1 +" r2 [1] $end
$var wire 1 ," r2 [0] $end
$var wire 1 w q2 [7] $end
$var wire 1 /" q2 [6] $end
$var wire 1 0" q2 [5] $end
$var wire 1 1" q2 [4] $end
$var wire 1 2" q2 [3] $end
$var wire 1 3" q2 [2] $end
$var wire 1 4" q2 [1] $end
$var wire 1 5" q2 [0] $end
$var wire 1 !! u2 [7] $end
$var wire 1 "! u2 [6] $end
$var wire 1 #! u2 [5] $end
$var wire 1 $! u2 [4] $end
$var wire 1 %! u2 [3] $end
$var wire 1 &! u2 [2] $end
$var wire 1 '! u2 [1] $end
$var wire 1 (! u2 [0] $end
$var wire 1 j! cr1 $end
$var wire 1 E" cq1 $end
$var wire 1 +! h2 [7] $end
$var wire 1 6" h2 [6] $end
$var wire 1 7" h2 [5] $end
$var wire 1 8" h2 [4] $end
$var wire 1 9" h2 [3] $end
$var wire 1 :" h2 [2] $end
$var wire 1 ;" h2 [1] $end
$var wire 1 <" h2 [0] $end
$var wire 1 3! clkena $end
$var wire 1 4! ADD $end
$var wire 1 5! ena $end
$var wire 1 6! aset $end
$var wire 1 7! sclr $end
$var wire 1 8! sset $end
$var wire 1 9! aload $end
$var wire 1 :! sload $end
$var wire 1 ;! aclr $end
$var wire 1 <! ovf1 $end
$var wire 1 =! cin1 $end
$var wire 1 C" U2 $end
$var reg 7 ?! I1 [6:0] $end
$var reg 7 @! I2 [6:0] $end
$var reg 8 A! I3 [7:0] $end
$var reg 8 B! I4 [7:0] $end
$var reg 15 C! s [14:0] $end
$scope module add_1 $end
$var wire 1 D! dataa [6] $end
$var wire 1 E! dataa [5] $end
$var wire 1 F! dataa [4] $end
$var wire 1 G! dataa [3] $end
$var wire 1 H! dataa [2] $end
$var wire 1 I! dataa [1] $end
$var wire 1 J! dataa [0] $end
$var wire 1 K! datab [6] $end
$var wire 1 L! datab [5] $end
$var wire 1 M! datab [4] $end
$var wire 1 N! datab [3] $end
$var wire 1 O! datab [2] $end
$var wire 1 P! datab [1] $end
$var wire 1 Q! datab [0] $end
$var wire 1 [! result [6] $end
$var wire 1 \! result [5] $end
$var wire 1 ]! result [4] $end
$var wire 1 ^! result [3] $end
$var wire 1 _! result [2] $end
$var wire 1 `! result [1] $end
$var wire 1 a! result [0] $end
$var wire 1 j! cout $end
$var wire 1 Z! cin $end
$upscope $end
$scope module reg_1 $end
$var wire 1 [! data [6] $end
$var wire 1 \! data [5] $end
$var wire 1 ]! data [4] $end
$var wire 1 ^! data [3] $end
$var wire 1 _! data [2] $end
$var wire 1 `! data [1] $end
$var wire 1 a! data [0] $end
$var wire 1 -" clock $end
$var reg 7 c! q [6:0] $end
$upscope $end
$scope module reg_2 $end
$var wire 1 d! data [6] $end
$var wire 1 e! data [5] $end
$var wire 1 f! data [4] $end
$var wire 1 g! data [3] $end
$var wire 1 h! data [2] $end
$var wire 1 i! data [1] $end
$var wire 1 j! data [0] $end
$var wire 1 -" clock $end
$var reg 7 l! q [6:0] $end
$upscope $end
$scope module add_2 $end
$var wire 1 m! dataa [6] $end
$var wire 1 n! dataa [5] $end
$var wire 1 o! dataa [4] $end
$var wire 1 p! dataa [3] $end
$var wire 1 q! dataa [2] $end
$var wire 1 r! dataa [1] $end
$var wire 1 s! dataa [0] $end
$var wire 1 t! datab [6] $end
$var wire 1 u! datab [5] $end
$var wire 1 v! datab [4] $end
$var wire 1 w! datab [3] $end
$var wire 1 x! datab [2] $end
$var wire 1 y! datab [1] $end
$var wire 1 z! datab [0] $end
$var wire 1 &" result [6] $end
$var wire 1 '" result [5] $end
$var wire 1 (" result [4] $end
$var wire 1 )" result [3] $end
$var wire 1 *" result [2] $end
$var wire 1 +" result [1] $end
$var wire 1 ," result [0] $end
$var wire 1 $" cout $end
$var wire 1 %" cin $end
$upscope $end
$scope module reg_3 $end
$var wire 1 &" data [6] $end
$var wire 1 '" data [5] $end
$var wire 1 (" data [4] $end
$var wire 1 )" data [3] $end
$var wire 1 *" data [2] $end
$var wire 1 +" data [1] $end
$var wire 1 ," data [0] $end
$var wire 1 -" clock $end
$var reg 7 ." q [6:0] $end
$upscope $end
$scope module add_3 $end
$var wire 1 /" dataa [6] $end
$var wire 1 0" dataa [5] $end
$var wire 1 1" dataa [4] $end
$var wire 1 2" dataa [3] $end
$var wire 1 3" dataa [2] $end
$var wire 1 4" dataa [1] $end
$var wire 1 5" dataa [0] $end
$var wire 1 6" datab [6] $end
$var wire 1 7" datab [5] $end
$var wire 1 8" datab [4] $end
$var wire 1 9" datab [3] $end
$var wire 1 :" datab [2] $end
$var wire 1 ;" datab [1] $end
$var wire 1 <" datab [0] $end
$var wire 1 =" result [6] $end
$var wire 1 >" result [5] $end
$var wire 1 ?" result [4] $end
$var wire 1 @" result [3] $end
$var wire 1 A" result [2] $end
$var wire 1 B" result [1] $end
$var wire 1 C" result [0] $end
$var wire 1 D" cout $end
$var wire 1 E" cin $end
$upscope $end
$upscope $end
$upscope $end
$enddefinitions $end
#0
$dumpvars
bx 0
bx 1
02
xV
xU
xT
xS
xR
xQ
xg
xf
x_
x^
xK!
zi!
zh!
zf!
xC
zZ!
zd!
xL
xF!
xJ
xE!
zg!
xI
ze!
xF
xB
xM
xI!
xG!
xK
xH!
xJ!
xD!
xQ!
xP!
xH
xG
0-"
xE
xD
xO!
xN!
xM!
xL!
x>"
xs!
x@"
xm!
x$"
xx!
xw!
xo!
xz!
xt!
x="
xr!
xn!
xD"
z%"
xp!
xB"
xu!
xy!
xq!
xA"
x?"
xv!
x]
x\
x[
xZ
xY
xX
xW
bx l!
bx ?!
bx @!
bx A!
bx B!
bx C!
x[!
xa!
x\!
xc
x^!
xd
x]!
xb
x+"
x("
xe
x,"
x*"
x)"
x`!
xa
x_!
x&"
z$!
x1"
x4"
x3"
z#!
0;"
08"
0+!
03!
06!
x5"
08!
15!
zo
z(!
xE"
z%!
09!
07"
x/"
zw
09"
z"!
xj!
06"
x2"
x0"
0:"
14!
07!
0<"
x'"
z&!
z!!
z'!
0;!
x:
x>
x8
x7
xC"
x6
x5
x4
x9
x3
xP
xO
xN
0:!
0=!
xA
x=
x@
x<
z<!
x;
x?
bx c!
bx ."
$end
#1000
12
zV
zU
zT
zS
zR
zQ
1-"
zX
zW
bzx l!
bzx C!
#2000
02
0-"
#3000
12
1-"
#4000
02
0-"
#5000
b1010 0
b0 1
12
0K!
0C
0L
0F!
0J
0E!
0I
0F
0B
0M
1I!
1G!
0K
0H!
0J!
0D!
0Q!
0P!
0H
0G
1-"
0E
0D
0O!
0N!
0M!
0L!
0s!
0m!
0$"
0x!
0w!
0o!
0z!
0t!
0r!
0n!
0p!
0u!
0y!
0q!
0v!
b1010 ?!
b0 @!
b0 A!
b0 B!
0[!
0a!
0\!
1^!
0]!
0+"
0("
0,"
0*"
0)"
1`!
0_!
0&"
0j!
0'"
0:
1>
08
07
06
05
04
09
03
0P
0O
0N
0A
0=
1@
0<
0;
0?
#6000
02
0-"
#7000
12
0g
1f
1-"
0>"
0@"
0="
0D"
0B"
0A"
0?"
bz0 l!
0c
1d
0b
0e
0a
01"
04"
03"
05"
0E"
0/"
02"
00"
0C"
b1010 c!
b0 ."
#8000
02
0-"
#9000
12
0_
1^
1-"
0]
1\
0[
0Z
0Y
bz0001010 C!
#10000
02
0-"
#11000
12
1-"
#12000
02
0-"
#13000
12
1-"
#14000
02
0-"
#15000
b1111101001 0
b1111101001 1
12
1K!
1J
1E!
1I
1M
0I!
1K
1J!
1D!
1Q!
1H
1G
1-"
1N!
1L!
1s!
1x!
1z!
1r!
1y!
1q!
b1101001 ?!
b1101001 @!
b111 A!
b111 B!
1[!
0^!
1]!
1+"
1*"
1)"
1j!
1:
18
19
1P
1A
0@
1<
1;
#16000
02
0-"
#17000
12
1-"
1@"
1B"
1A"
bz1 l!
1c
0d
1a
14"
13"
1E"
12"
b1010010 c!
b1110 ."
#18000
02
0-"
#19000
12
1-"
0\
1[
1Y
bz1010010 C!
#20000
02
0-"
#21000
12
1-"
#22000
02
0-"
#23000
12
1-"
#24000
02
0-"
#25000
b11110000010111 0
b11110000101010 1
12
0K!
1C
1F!
0J
0E!
0I
1F
1I!
0G!
1H!
0D!
0Q!
1P!
0H
0G
1-"
1E
1D
0s!
1m!
1$"
0x!
1w!
1o!
0z!
1t!
0r!
1n!
1p!
1u!
0y!
0q!
1v!
b10111 ?!
b101010 @!
b1111000 A!
b1111000 B!
1a!
0]!
0+"
1("
0*"
0)"
0`!
1&"
0j!
1'"
0:
0>
08
17
16
15
14
09
0P
1O
1=
1@
0<
0;
1?
#26000
02
0-"
#27000
12
1g
0f
1-"
1>"
0@"
1="
0B"
0A"
1?"
bz0 l!
0c
11"
04"
03"
0E"
1/"
02"
10"
b1000001 c!
b1110000 ."
#28000
02
0-"
#29000
12
1_
0^
1-"
0[
bz1000001 C!
#30000
02
0-"
#31000
12
1-"
#32000
02
0-"
#33000
12
1-"
#34000
02
0-"
#35000
b11111010000011 0
b1111111111 1
12
1K!
0C
1L
0F!
1J
1I
0F
0H!
1Q!
1H
1G
1-"
0E
0D
1O!
1M!
1s!
1x!
0w!
1z!
0t!
0u!
1y!
1q!
0v!
b11 ?!
b1111111 @!
b1111101 A!
b111 B!
0[!
0a!
0("
1*"
1`!
0&"
1j!
0'"
1:
18
1P
1N
0=
0?
#36000
02
0-"
#37000
12
0g
1f
1-"
0>"
0="
1A"
0?"
bz1 l!
0a
01"
13"
1E"
0/"
00"
b10 c!
b100 ."
#38000
02
0-"
#39000
12
0_
1^
1-"
0Y
bz0000010 C!
